NumIntKHK/__init__.py
NumIntKHK/ceros_pesos_cuad_gauss.py
NumIntKHK/gaussiana.py
NumIntKHK/gaussiana_compuesta.py
NumIntKHK/gaussiana_compuesta_iterativa.py
NumIntKHK/romberg.py
NumIntKHK/simpson.py
NumIntKHK/simpson_compuesto.py
NumIntKHK/simpson_compuesto_iterativo.py
NumIntKHK/trapecio.py
NumIntKHK/trapecio_compuesto.py
NumIntKHK/trapecio_compuesto_iterativo.py
NumIntKHK-0.0.4.dist-info/METADATA
NumIntKHK-0.0.4.dist-info/WHEEL
NumIntKHK-0.0.4.dist-info/top_level.txt
NumIntKHK-0.0.4.dist-info/RECORD
